{
    "name": "Cancha",
    "fields": [
        {
            "fieldName": "nombre",
            "fieldType": "String",
            "fieldValidateRules": [
                "required"
            ]
        },
        {
            "fieldName": "descripcion",
            "fieldType": "String"
        },
        {
            "fieldName": "direccion",
            "fieldType": "String",
            "fieldValidateRules": [
                "required"
            ]
        },
        {
            "fieldName": "ubicacion",
            "fieldType": "String",
            "fieldValidateRules": [
                "required"
            ]
        },
        {
            "fieldName": "imagen",
            "fieldType": "byte[]",
            "fieldTypeBlobContent": "image"
        },
        {
            "fieldName": "fechaCreacion",
            "fieldType": "Instant"
        },
        {
            "fieldName": "estado",
            "fieldType": "Boolean",
            "fieldValidateRules": [
                "required"
            ]
        }
    ],
    "relationships": [
        {
            "relationshipType": "many-to-one",
            "otherEntityName": "tipoCancha",
            "otherEntityRelationshipName": "cancha",
            "relationshipName": "tipoCancha",
            "otherEntityField": "id"
        }
    ],
    "changelogDate": "20200525050300",
    "entityTableName": "cancha",
    "dto": "no",
    "pagination": "pagination",
    "service": "no",
    "jpaMetamodelFiltering": false,
    "fluentMethods": true,
    "readOnly": false,
    "embedded": false,
    "clientRootFolder": "",
    "applications": "*"
}